tink_custom-1.7.1.dist-info/METADATA
tink_custom-1.7.1.dist-info/WHEEL
tink_custom-1.7.1.dist-info/top_level.txt
tink_custom-1.7.1.dist-info/RECORD
tink/cleartext_keyset_handle.py
tink/tink_config_test.py
tink/_keyset_reader_test.py
tink/cleartext_keyset_handle_test.py
tink/__init__.py
tink/tink_config.py
tink/_keyset_writer.py
tink/_keyset_reader.py
tink/_keyset_writer_test.py
tink/secret_key_access_test.py
tink/secret_key_access.py
tink/_keyset_handle_test.py
tink/_keyset_handle.py
tink/mac/_mac_key_manager_test.py
tink/mac/_mac_wrapper_test.py
tink/mac/__init__.py
tink/mac/_mac_wrapper.py
tink/mac/_mac.py
tink/mac/_mac_key_templates_test.py
tink/mac/_mac_key_manager.py
tink/mac/_mac_key_templates.py
tink/testing/fake_kms_test.py
tink/testing/bytes_io_test.py
tink/testing/helper.py
tink/testing/__init__.py
tink/testing/keyset_builder.py
tink/testing/fake_kms.py
tink/testing/helper_test.py
tink/testing/keyset_builder_test.py
tink/testing/bytes_io.py
tink/core/_tink_error.py
tink/core/_primitive_set.py
tink/core/__init__.py
tink/core/_registry_test.py
tink/core/_crypto_format.py
tink/core/_crypto_format_test.py
tink/core/_registry.py
tink/core/_primitive_set_test.py
tink/core/_key_manager.py
tink/core/_primitive_wrapper.py
tink/jwt/_raw_jwt.py
tink/jwt/_jwt_key_templates_test.py
tink/jwt/_jwt_hmac_key_manager_test.py
tink/jwt/_jwt_public_key_sign.py
tink/jwt/_jwt_mac_wrapper.py
tink/jwt/_json_util_test.py
tink/jwt/_jwt_validator.py
tink/jwt/_jwt_signature_wrappers_test.py
tink/jwt/_json_util.py
tink/jwt/_jwt_signature_key_manager.py
tink/jwt/_jwk_set_converter.py
tink/jwt/_jwt_error.py
tink/jwt/__init__.py
tink/jwt/_jwt_mac_wrapper_test.py
tink/jwt/_jwt_signature_key_manager_test.py
tink/jwt/_jwk_set_converter_test.py
tink/jwt/_jwt_hmac_key_manager.py
tink/jwt/_jwt_format.py
tink/jwt/_jwt_public_key_verify.py
tink/jwt/_verified_jwt.py
tink/jwt/_jwt_mac.py
tink/jwt/_raw_jwt_test.py
tink/jwt/_jwt_validator_test.py
tink/jwt/_jwt_signature_wrappers.py
tink/jwt/_verified_jwt_test.py
tink/jwt/_jwt_key_templates.py
tink/jwt/_jwt_format_test.py
