Metadata-Version: 2.1
Name: tink-custom
Version: 1.7.1
Summary: A multi-language, cross-platform library that provides cryptographic APIs that are secure, easy to use correctly, and hard(er) to misuse.
Home-page: https://github.com/google/tink
Author: Tink Developers
Author-email: tink-users@googlegroups.com
License: Apache 2.0
Keywords: tink cryptography
Classifier: Programming Language :: Python :: 3.7
Classifier: Programming Language :: Python :: 3.8
Classifier: Programming Language :: Python :: 3.9
Classifier: Topic :: Software Development :: Libraries
Requires-Dist: absl-py (==1.3.0)
Requires-Dist: protobuf (==4.21.9)
